era_5g_tf2json/__init__.py
era_5g_tf2json/py.typed
era_5g_tf2json/tf2_web_republisher.py
era_5g_tf2json/tf_pair.py
era_5g_tf2json-0.2.1.dist-info/METADATA
era_5g_tf2json-0.2.1.dist-info/WHEEL
era_5g_tf2json-0.2.1.dist-info/namespace_packages.txt
era_5g_tf2json-0.2.1.dist-info/top_level.txt
era_5g_tf2json-0.2.1.dist-info/RECORD
