Metadata-Version: 2.1
Name: era-5g-tf2json
Version: 0.2.1
Summary: Library to convert ROS2 TF into a JSON.
Author: Zdenek Materna
Author-email: imaterna@fit.vut.cz
License: LGPL
Classifier: Programming Language :: Python :: 3
Classifier: License :: OSI Approved :: GNU Lesser General Public License v3 (LGPLv3)
Classifier: Operating System :: OS Independent
Classifier: Intended Audience :: Developers
Requires-Python: >=3.8
Requires-Dist: numpy (~=1.24.2)
Requires-Dist: pyquaternion (~=0.9.9)
